jupyterlab_wakatime/__init__.py
jupyterlab_wakatime/_version.py
jupyterlab_wakatime/handlers.py
jupyterlab_wakatime/wakatime.py
jupyterlab_wakatime-0.1.4.data/data/etc/jupyter/jupyter_server_config.d/jupyterlab_wakatime.json
jupyterlab_wakatime-0.1.4.data/data/share/jupyter/labextensions/jupyterlab-wakatime/package.json
jupyterlab_wakatime-0.1.4.data/data/share/jupyter/labextensions/jupyterlab-wakatime/static/183.2d6897153e15a15dcf58.js
jupyterlab_wakatime-0.1.4.data/data/share/jupyter/labextensions/jupyterlab-wakatime/static/747.cdaa9d803514f688620b.js
jupyterlab_wakatime-0.1.4.data/data/share/jupyter/labextensions/jupyterlab-wakatime/static/remoteEntry.0676deda90cc449331b2.js
jupyterlab_wakatime-0.1.4.data/data/share/jupyter/labextensions/jupyterlab-wakatime/static/style.js
jupyterlab_wakatime-0.1.4.data/data/share/jupyter/labextensions/jupyterlab-wakatime/static/third-party-licenses.json
jupyterlab_wakatime-0.1.4.data/data/share/jupyter/labextensions/jupyterlab-wakatime/install.json
jupyterlab_wakatime-0.1.4.dist-info/METADATA
jupyterlab_wakatime-0.1.4.dist-info/WHEEL
jupyterlab_wakatime-0.1.4.dist-info/licenses/LICENSE
jupyterlab_wakatime-0.1.4.dist-info/RECORD
