Metadata-Version: 2.1
Name: jupyterlab_wakatime
Version: 0.1.4
Summary: A JupyterLab WakaTime extension.
Project-URL: Homepage, https://github.com/wakatime/jupyterlab-wakatime
Project-URL: Bug Tracker, https://github.com/wakatime/jupyterlab-wakatime/issues
Project-URL: Repository, https://github.com/wakatime/jupyterlab-wakatime.git
Author-email: Allan Chain <allan-chain@outllok.com>
License: BSD 3-Clause License
License-File: LICENSE
Classifier: Framework :: Jupyter
Classifier: Framework :: Jupyter :: JupyterLab
Classifier: Framework :: Jupyter :: JupyterLab :: 4
Classifier: Framework :: Jupyter :: JupyterLab :: Extensions
Classifier: Framework :: Jupyter :: JupyterLab :: Extensions :: Prebuilt
Classifier: License :: OSI Approved :: BSD License
Classifier: Programming Language :: Python
Classifier: Programming Language :: Python :: 3
Classifier: Programming Language :: Python :: 3.8
Classifier: Programming Language :: Python :: 3.9
Classifier: Programming Language :: Python :: 3.10
Classifier: Programming Language :: Python :: 3.11
Classifier: Programming Language :: Python :: 3.12
Requires-Python: >=3.8
Requires-Dist: jupyter-server<3,>=2.0.1
